metarace_ttstart-1.0.3.dist-info/licenses/LICENSE
ttstart/__init__.py
ttstart/__main__.py
ttstart/start.wav
metarace_ttstart-1.0.3.dist-info/METADATA
metarace_ttstart-1.0.3.dist-info/WHEEL
metarace_ttstart-1.0.3.dist-info/entry_points.txt
metarace_ttstart-1.0.3.dist-info/top_level.txt
metarace_ttstart-1.0.3.dist-info/RECORD
