Metadata-Version: 2.4
Name: metarace-ttstart
Version: 1.0.3
Summary: Time Trial Start Console
Author-email: Nathan Fraser <ndf-zz@6-v.org>
License-Expression: MIT
Project-URL: homepage, https://github.com/ndf-zz/metarace-ttstart
Keywords: TT,start
Classifier: Development Status :: 3 - Alpha
Classifier: Topic :: Other/Nonlisted Topic
Classifier: Operating System :: OS Independent
Classifier: Programming Language :: Python :: 3
Requires-Python: >=3.11
License-File: LICENSE
Requires-Dist: metarace<2.2,>=2.1.20
Dynamic: license-file
